{
  "fixtures": [
    {
      "id": "LALIGA-001",
      "league": {"code": "LALIGA", "name": "LaLiga", "region": "eu"},
      "date_utc": "2025-10-07T19:00:00Z",
      "home": {"id": "ATM", "name": "Atlético Madrid", "city": "Madrid"},
      "away": {"id": "SEV", "name": "Sevilla", "city": "Sevilla"},
      "home_cards_pg": 2.5,
      "away_cards_pg": 2.3,
      "referee_cards_pg": 5.6,
      "derby": false,
      "knockout": false,
      "intl_comp_bonus": 0.0,
      "home_fh_goals_pg": 0.7,
      "away_fh_goals_pg": 0.6,
      "home_shots_on_target_pg": 5.1,
      "away_shots_on_target_pg": 4.6,
      "ranking_diff": 0.4,
      "weather_penalty": 0.0,
      "congestion_penalty": 0.0
    },
    {
      "id": "LIB-101",
      "league": {"code": "LIBERTADORES", "name": "Copa Libertadores", "region": "conmebol"},
      "date_utc": "2025-10-06T23:30:00Z",
      "home": {"id": "BOC", "name": "Boca Juniors", "city": "Buenos Aires"},
      "away": {"id": "RIV", "name": "River Plate", "city": "Buenos Aires"},
      "home_cards_pg": 3.2,
      "away_cards_pg": 3.0,
      "referee_cards_pg": 5.8,
      "derby": true,
      "knockout": true,
      "intl_comp_bonus": 0.35,
      "home_fh_goals_pg": 0.8,
      "away_fh_goals_pg": 0.7,
      "home_shots_on_target_pg": 5.5,
      "away_shots_on_target_pg": 5.2,
      "ranking_diff": 0.2,
      "weather_penalty": 0.0,
      "congestion_penalty": 0.05
    },
    {
      "id": "BUND-050",
      "league": {"code": "BUNDES", "name": "Bundesliga", "region": "eu"},
      "date_utc": "2025-10-08T18:30:00Z",
      "home": {"id": "BVB", "name": "Dortmund", "city": "Dortmund"},
      "away": {"id": "SCF", "name": "Freiburg", "city": "Freiburg"},
      "home_cards_pg": 1.7,
      "away_cards_pg": 1.6,
      "referee_cards_pg": 3.8,
      "derby": false,
      "knockout": false,
      "intl_comp_bonus": 0.0,
      "home_fh_goals_pg": 0.9,
      "away_fh_goals_pg": 0.5,
      "home_shots_on_target_pg": 6.2,
      "away_shots_on_target_pg": 3.7,
      "ranking_diff": 0.8,
      "weather_penalty": 0.0,
      "congestion_penalty": 0.0
    }
  ]
}
